{
  "entite_0": {
    "label": "PER",
    "text": "J&#x27;espere",
    "jalons": [
      0,
      13
    ]
  },
  "entite_1": {
    "label": "LOC",
    "text": "L&quot",
    "jalons": [
      111,
      117
    ]
  },
  "entite_2": {
    "label": "PER",
    "text": "Monsieur",
    "jalons": [
      264,
      272
    ]
  },
  "entite_3": {
    "label": "LOC",
    "text": "Rochefort p^r",
    "jalons": [
      346,
      359
    ]
  },
  "entite_4": {
    "label": "PER",
    "text": "p^r Conduire",
    "jalons": [
      450,
      462
    ]
  },
  "entite_5": {
    "label": "LOC",
    "text": "p^r",
    "jalons": [
      484,
      487
    ]
  },
  "entite_6": {
    "label": "MISC",
    "text": "S^t",
    "jalons": [
      500,
      503
    ]
  },
  "entite_7": {
    "label": "MISC",
    "text": "Cause de grands malheurs dieu",
    "jalons": [
      621,
      650
    ]
  },
  "entite_8": {
    "label": "MISC",
    "text": "Bons souvernir &amp",
    "jalons": [
      905,
      924
    ]
  },
  "entite_9": {
    "label": "PER",
    "text": "jay l&#x27;honneur",
    "jalons": [
      958,
      976
    ]
  },
  "entite_10": {
    "label": "LOC",
    "text": "Respectueux",
    "jalons": [
      1015,
      1026
    ]
  },
  "entite_11": {
    "label": "PER",
    "text": "Monsieur",
    "jalons": [
      1027,
      1035
    ]
  },
  "entite_12": {
    "label": "LOC",
    "text": "m^t",
    "jalons": [
      1318,
      1321
    ]
  },
  "entite_13": {
    "label": "MISC",
    "text": "Vôtre tres humble &amp",
    "jalons": [
      1335,
      1357
    ]
  },
  "entite_14": {
    "label": "MISC",
    "text": "p^r decharge &amp",
    "jalons": [
      1364,
      1381
    ]
  },
  "entite_15": {
    "label": "LOC",
    "text": "p^r",
    "jalons": [
      1508,
      1511
    ]
  },
  "entite_16": {
    "label": "LOC",
    "text": "Charet",
    "jalons": [
      1572,
      1578
    ]
  },
  "entite_17": {
    "label": "LOC",
    "text": "Nantes",
    "jalons": [
      1692,
      1698
    ]
  },
  "entite_18": {
    "label": "LOC",
    "text": "p^r",
    "jalons": [
      1721,
      1724
    ]
  },
  "entite_19": {
    "label": "LOC",
    "text": "Jullie",
    "jalons": [
      1728,
      1734
    ]
  },
  "entite_20": {
    "label": "LOC",
    "text": "J&#x27;espere",
    "jalons": [
      1781,
      1794
    ]
  },
  "entite_21": {
    "label": "PER",
    "text": "Compte de Vente",
    "jalons": [
      2019,
      2034
    ]
  },
  "entite_22": {
    "label": "MISC",
    "text": "Net Produit",
    "jalons": [
      2038,
      2049
    ]
  },
  "entite_23": {
    "label": "MISC",
    "text": "Bq̃ues",
    "jalons": [
      2056,
      2062
    ]
  },
  "entite_24": {
    "label": "MISC",
    "text": "Monsieur Bretton",
    "jalons": [
      2113,
      2129
    ]
  },
  "entite_25": {
    "label": "LOC",
    "text": "Cul de Sac",
    "jalons": [
      2147,
      2157
    ]
  },
  "entite_26": {
    "label": "PER",
    "text": "Messieurs",
    "jalons": [
      2173,
      2182
    ]
  },
  "entite_27": {
    "label": "LOC",
    "text": "Minerve Cap^ne Moreau",
    "jalons": [
      2224,
      2245
    ]
  },
  "entite_28": {
    "label": "LOC",
    "text": "Savoir",
    "jalons": [
      2324,
      2330
    ]
  },
  "entite_29": {
    "label": "LOC",
    "text": "Mars",
    "jalons": [
      2331,
      2335
    ]
  },
  "entite_30": {
    "label": "ORG",
    "text": "Bq̃ues",
    "jalons": [
      2344,
      2350
    ]
  },
  "entite_31": {
    "label": "PER",
    "text": "Kuster",
    "jalons": [
      2373,
      2379
    ]
  },
  "entite_32": {
    "label": "LOC",
    "text": "Pelloutier pez^te",
    "jalons": [
      2383,
      2400
    ]
  },
  "entite_33": {
    "label": "LOC",
    "text": "p^r",
    "jalons": [
      2591,
      2594
    ]
  },
  "entite_34": {
    "label": "LOC",
    "text": "d^e",
    "jalons": [
      2676,
      2679
    ]
  },
  "entite_35": {
    "label": "LOC",
    "text": "Frouet",
    "jalons": [
      2710,
      2716
    ]
  },
  "entite_36": {
    "label": "LOC",
    "text": "Bq̃ues",
    "jalons": [
      2866,
      2872
    ]
  },
  "entite_37": {
    "label": "LOC",
    "text": "L&quot",
    "jalons": [
      2894,
      2900
    ]
  },
  "entite_38": {
    "label": "LOC",
    "text": "Frais",
    "jalons": [
      2915,
      2920
    ]
  },
  "entite_39": {
    "label": "LOC",
    "text": "Lt",
    "jalons": [
      2983,
      2985
    ]
  },
  "entite_40": {
    "label": "MISC",
    "text": "M^e",
    "jalons": [
      3026,
      3029
    ]
  },
  "entite_41": {
    "label": "MISC",
    "text": "net sucre terré donn^e 3 1/2",
    "jalons": [
      3177,
      3205
    ]
  },
  "entite_42": {
    "label": "LOC",
    "text": "2^s p^r L.",
    "jalons": [
      3226,
      3236
    ]
  },
  "entite_43": {
    "label": "LOC",
    "text": "3 p^r",
    "jalons": [
      3241,
      3246
    ]
  },
  "entite_44": {
    "label": "LOC",
    "text": "Le m^e",
    "jalons": [
      3365,
      3371
    ]
  },
  "entite_45": {
    "label": "LOC",
    "text": "p^r",
    "jalons": [
      3410,
      3413
    ]
  },
  "entite_46": {
    "label": "LOC",
    "text": "Magazinage",
    "jalons": [
      3490,
      3500
    ]
  },
  "entite_47": {
    "label": "LOC",
    "text": "p^r Escompte",
    "jalons": [
      3565,
      3577
    ]
  },
  "entite_48": {
    "label": "LOC",
    "text": "2 p^r",
    "jalons": [
      3602,
      3607
    ]
  },
  "entite_49": {
    "label": "LOC",
    "text": "Commission",
    "jalons": [
      3635,
      3645
    ]
  },
  "entite_50": {
    "label": "LOC",
    "text": "2 p^r",
    "jalons": [
      3648,
      3653
    ]
  },
  "entite_51": {
    "label": "PER",
    "text": "Monsieur",
    "jalons": [
      3735,
      3743
    ]
  },
  "entite_52": {
    "label": "PER",
    "text": "Rochefoucauld Bayers",
    "jalons": [
      3761,
      3781
    ]
  },
  "entite_53": {
    "label": "MISC",
    "text": "Net",
    "jalons": [
      3817,
      3820
    ]
  },
  "entite_54": {
    "label": "MISC",
    "text": "La Somme de Six",
    "jalons": [
      3839,
      3854
    ]
  },
  "entite_55": {
    "label": "LOC",
    "text": "Nantes",
    "jalons": [
      3923,
      3929
    ]
  },
  "entite_56": {
    "label": "LOC",
    "text": "Mars",
    "jalons": [
      3936,
      3940
    ]
  },
  "entite_57": {
    "label": "LOC",
    "text": "Charet",
    "jalons": [
      3951,
      3957
    ]
  },
  "entite_58": {
    "label": "PER",
    "text": "Mrs Kuster",
    "jalons": [
      3970,
      3980
    ]
  },
  "entite_59": {
    "label": "PER",
    "text": "Pelloutier",
    "jalons": [
      3984,
      3994
    ]
  },
  "entite_60": {
    "label": "LOC",
    "text": "Paris",
    "jalons": [
      4066,
      4071
    ]
  },
  "entite_61": {
    "label": "LOC",
    "text": "p^r",
    "jalons": [
      4124,
      4127
    ]
  }
}