{
  "voc_eval_res": {
    "precision": 36.5854,
    "recall": 88.2353,
    "f-score": 51.7241
  },
  "KL_res": {
    "KL divergence": 1.0183092953723345,
    "Euclidean Dist.": 0.2514577995027156,
    "WER": 1.894736842105263,
    "CER": 1.3277310924369747,
    "Cosine Dist.": 0.2971511048110924
  },
  "occ_eval_res": {
    "precision": 32.0,
    "recall": 84.2105,
    "f-score": 46.3768
  },
  "clean_eval": {
    "f-score": 54.54545454545454,
    "precision": 58.285714285714285,
    "recall": 51.256281407035175,
    "tp": 102,
    "fp": 73,
    "fn": 97
  },
  "jaccard": [
    0.605
  ],
  "braycurtis": [
    0.5062972292191436
  ],
  "dice": [
    0.4336917562724014
  ],
  "cosinus": [
    0.2878713464622591
  ]
}