{
  "entite_0": {
    "label": "LOC",
    "text": "Brest",
    "jalons": [
      2,
      7
    ]
  },
  "entite_1": {
    "label": "MISC",
    "text": "Piece",
    "jalons": [
      33,
      38
    ]
  },
  "entite_2": {
    "label": "MISC",
    "text": "Ma Chere petite",
    "jalons": [
      61,
      76
    ]
  },
  "entite_3": {
    "label": "PER",
    "text": "N. N.",
    "jalons": [
      240,
      245
    ]
  },
  "entite_4": {
    "label": "MISC",
    "text": "Vice Amiral",
    "jalons": [
      333,
      344
    ]
  },
  "entite_5": {
    "label": "ORG",
    "text": "M^r",
    "jalons": [
      472,
      475
    ]
  },
  "entite_6": {
    "label": "MISC",
    "text": "Sçéaux",
    "jalons": [
      490,
      496
    ]
  },
  "entite_7": {
    "label": "PER",
    "text": "le Roy",
    "jalons": [
      525,
      531
    ]
  },
  "entite_8": {
    "label": "PER",
    "text": "Reine",
    "jalons": [
      650,
      655
    ]
  },
  "entite_9": {
    "label": "PER",
    "text": "Bouclier",
    "jalons": [
      696,
      704
    ]
  },
  "entite_10": {
    "label": "MISC",
    "text": "S^r fustel",
    "jalons": [
      963,
      973
    ]
  },
  "entite_11": {
    "label": "PER",
    "text": "M^r Fevier",
    "jalons": [
      1485,
      1495
    ]
  }
}