{
  "entite_0": {
    "label": "PER",
    "text": "reud",
    "jalons": [
      0,
      4
    ]
  },
  "entite_1": {
    "label": "MISC",
    "text": "ieres",
    "jalons": [
      99,
      104
    ]
  },
  "entite_2": {
    "label": "PER",
    "text": "Colonel",
    "jalons": [
      220,
      227
    ]
  },
  "entite_3": {
    "label": "MISC",
    "text": "sollicité",
    "jalons": [
      244,
      254
    ]
  },
  "entite_4": {
    "label": "ORG",
    "text": "M^rs",
    "jalons": [
      420,
      424
    ]
  },
  "entite_5": {
    "label": "PER",
    "text": "Maupoint",
    "jalons": [
      443,
      451
    ]
  },
  "entite_6": {
    "label": "PER",
    "text": "Jaloux",
    "jalons": [
      474,
      480
    ]
  },
  "entite_7": {
    "label": "PER",
    "text": "Roy",
    "jalons": [
      502,
      505
    ]
  },
  "entite_8": {
    "label": "MISC",
    "text": "S&#39;il",
    "jalons": [
      908,
      916
    ]
  },
  "entite_9": {
    "label": "PER",
    "text": "Monseigneur",
    "jalons": [
      934,
      945
    ]
  },
  "entite_10": {
    "label": "ORG",
    "text": "désespoir",
    "jalons": [
      1155,
      1165
    ]
  },
  "entite_11": {
    "label": "MISC",
    "text": "pitié",
    "jalons": [
      1186,
      1192
    ]
  },
  "entite_12": {
    "label": "MISC",
    "text": "eû",
    "jalons": [
      1273,
      1276
    ]
  },
  "entite_13": {
    "label": "ORG",
    "text": "Rep",
    "jalons": [
      1516,
      1519
    ]
  },
  "entite_14": {
    "label": "LOC",
    "text": "S^t",
    "jalons": [
      1528,
      1531
    ]
  },
  "entite_15": {
    "label": "ORG",
    "text": "X",
    "jalons": [
      1554,
      1555
    ]
  },
  "entite_16": {
    "label": "LOC",
    "text": "J&#39;invoque",
    "jalons": [
      1570,
      1583
    ]
  },
  "entite_17": {
    "label": "PER",
    "text": "Monseigneur",
    "jalons": [
      1703,
      1714
    ]
  }
}