{
  "entite_0": {
    "label": "MISC",
    "text": "Interrogatoire du vingt",
    "jalons": [
      23,
      46
    ]
  },
  "entite_1": {
    "label": "MISC",
    "text": "uniême Septembre Mil",
    "jalons": [
      47,
      68
    ]
  },
  "entite_2": {
    "label": "MISC",
    "text": "verité",
    "jalons": [
      112,
      119
    ]
  },
  "entite_3": {
    "label": "PER",
    "text": "Avons",
    "jalons": [
      163,
      168
    ]
  },
  "entite_4": {
    "label": "MISC",
    "text": "Carbonns",
    "jalons": [
      201,
      209
    ]
  },
  "entite_5": {
    "label": "PER",
    "text": "pierre dorlé",
    "jalons": [
      239,
      252
    ]
  },
  "entite_6": {
    "label": "PER",
    "text": "duplessis Joseph Le Conte",
    "jalons": [
      257,
      282
    ]
  },
  "entite_7": {
    "label": "PER",
    "text": "nicolas Besnard Tous",
    "jalons": [
      287,
      307
    ]
  },
  "entite_8": {
    "label": "MISC",
    "text": "Temoins",
    "jalons": [
      314,
      321
    ]
  },
  "entite_9": {
    "label": "PER",
    "text": "Luy Avons demandé",
    "jalons": [
      333,
      351
    ]
  },
  "entite_10": {
    "label": "MISC",
    "text": "Biens",
    "jalons": [
      403,
      408
    ]
  },
  "entite_11": {
    "label": "MISC",
    "text": "L&#39;avertiosant",
    "jalons": [
      410,
      427
    ]
  },
  "entite_12": {
    "label": "MISC",
    "text": "Reproches",
    "jalons": [
      521,
      530
    ]
  },
  "entite_13": {
    "label": "MISC",
    "text": "Fait par le Conseil de guerre",
    "jalons": [
      608,
      637
    ]
  },
  "entite_14": {
    "label": "MISC",
    "text": "Conclasions",
    "jalons": [
      639,
      650
    ]
  },
  "entite_15": {
    "label": "LOC",
    "text": "Mor",
    "jalons": [
      654,
      657
    ]
  },
  "entite_16": {
    "label": "LOC",
    "text": "Ch^er",
    "jalons": [
      661,
      666
    ]
  }
}