{
  "entite_0": {
    "label": "LOC",
    "text": "anglois",
    "jalons": [
      22,
      29
    ]
  },
  "entite_1": {
    "label": "PER",
    "text": "aucunnes",
    "jalons": [
      110,
      118
    ]
  },
  "entite_2": {
    "label": "PER",
    "text": "moy vôtre cœur",
    "jalons": [
      138,
      152
    ]
  },
  "entite_3": {
    "label": "PER",
    "text": "j&#x27;ai",
    "jalons": [
      214,
      223
    ]
  },
  "entite_4": {
    "label": "MISC",
    "text": "desir sincere",
    "jalons": [
      244,
      257
    ]
  },
  "entite_5": {
    "label": "ORG",
    "text": "chere",
    "jalons": [
      333,
      338
    ]
  },
  "entite_6": {
    "label": "PER",
    "text": "laime",
    "jalons": [
      355,
      360
    ]
  },
  "entite_7": {
    "label": "PER",
    "text": "nieces",
    "jalons": [
      382,
      388
    ]
  },
  "entite_8": {
    "label": "PER",
    "text": "Compliment",
    "jalons": [
      429,
      439
    ]
  },
  "entite_9": {
    "label": "PER",
    "text": "L&#x27;abbé",
    "jalons": [
      442,
      453
    ]
  },
  "entite_10": {
    "label": "LOC",
    "text": "L&#x27;enfant",
    "jalons": [
      503,
      516
    ]
  },
  "entite_11": {
    "label": "LOC",
    "text": "M^r charet",
    "jalons": [
      529,
      539
    ]
  },
  "entite_12": {
    "label": "PER",
    "text": "G. L.",
    "jalons": [
      682,
      687
    ]
  },
  "entite_13": {
    "label": "MISC",
    "text": "Comtesse",
    "jalons": [
      784,
      792
    ]
  },
  "entite_14": {
    "label": "PER",
    "text": "Chabannes",
    "jalons": [
      796,
      805
    ]
  }
}