{
  "voc_eval_res": {
    "precision": 34.2105,
    "recall": 40.0,
    "f-score": 36.8794
  },
  "KL_res": {
    "KL divergence": 2.3821722015292863,
    "Euclidean Dist.": 0.12466392781622851,
    "WER": 0.9883720930232558,
    "CER": 0.6380597014925373,
    "Cosine Dist.": 0.19124432957148574
  },
  "occ_eval_res": {
    "precision": 38.4615,
    "recall": 46.5116,
    "f-score": 42.1053
  },
  "clean_eval": {
    "f-score": 28.85844748858447,
    "precision": 28.51985559566787,
    "recall": 29.20517560073937,
    "tp": 158,
    "fp": 396,
    "fn": 383
  },
  "jaccard": [
    0.5375
  ],
  "braycurtis": [
    0.3247721623860812
  ],
  "dice": [
    0.36752136752136755
  ],
  "cosinus": [
    0.11759167943618964
  ]
}