{
  "entite_0": {
    "label": "MISC",
    "text": "travail &amp",
    "jalons": [
      186,
      198
    ]
  },
  "entite_1": {
    "label": "LOC",
    "text": "acclimalé",
    "jalons": [
      200,
      210
    ]
  },
  "entite_2": {
    "label": "MISC",
    "text": "Je von feraiencore cette anné",
    "jalons": [
      252,
      282
    ]
  },
  "entite_3": {
    "label": "MISC",
    "text": "40 Daiques",
    "jalons": [
      305,
      315
    ]
  },
  "entite_4": {
    "label": "MISC",
    "text": "Connencemen",
    "jalons": [
      361,
      372
    ]
  },
  "entite_5": {
    "label": "ORG",
    "text": "Robion de lavrignais",
    "jalons": [
      483,
      503
    ]
  },
  "entite_6": {
    "label": "PER",
    "text": "J&#39;ai",
    "jalons": [
      637,
      645
    ]
  },
  "entite_7": {
    "label": "ORG",
    "text": "l&#39;h^n",
    "jalons": [
      703,
      712
    ]
  },
  "entite_8": {
    "label": "MISC",
    "text": "liberté",
    "jalons": [
      738,
      746
    ]
  },
  "entite_9": {
    "label": "LOC",
    "text": "solemnité",
    "jalons": [
      852,
      862
    ]
  },
  "entite_10": {
    "label": "LOC",
    "text": "m&#39;a",
    "jalons": [
      905,
      912
    ]
  },
  "entite_11": {
    "label": "MISC",
    "text": "ajuré",
    "jalons": [
      937,
      943
    ]
  },
  "entite_12": {
    "label": "MISC",
    "text": "taché",
    "jalons": [
      973,
      979
    ]
  },
  "entite_13": {
    "label": "PER",
    "text": "m&#39;avis envoyé",
    "jalons": [
      1210,
      1228
    ]
  },
  "entite_14": {
    "label": "LOC",
    "text": "constitüe",
    "jalons": [
      1233,
      1243
    ]
  },
  "entite_15": {
    "label": "LOC",
    "text": "Colonie",
    "jalons": [
      1437,
      1444
    ]
  },
  "entite_16": {
    "label": "MISC",
    "text": "vereté",
    "jalons": [
      1563,
      1570
    ]
  },
  "entite_17": {
    "label": "MISC",
    "text": "m^eme",
    "jalons": [
      1603,
      1608
    ]
  },
  "entite_18": {
    "label": "PER",
    "text": "Codere",
    "jalons": [
      1612,
      1618
    ]
  },
  "entite_19": {
    "label": "LOC",
    "text": "m^r",
    "jalons": [
      2043,
      2046
    ]
  },
  "entite_20": {
    "label": "MISC",
    "text": "prejugé Barbare",
    "jalons": [
      2179,
      2195
    ]
  },
  "entite_21": {
    "label": "MISC",
    "text": "Leogane",
    "jalons": [
      2392,
      2399
    ]
  }
}