{
  "entite_0": {
    "label": "LOC",
    "text": "Connoissances",
    "jalons": [
      17,
      30
    ]
  },
  "entite_1": {
    "label": "MISC",
    "text": "Jean",
    "jalons": [
      56,
      60
    ]
  },
  "entite_2": {
    "label": "PER",
    "text": "Dumas",
    "jalons": [
      82,
      87
    ]
  },
  "entite_3": {
    "label": "PER",
    "text": "A Repondu",
    "jalons": [
      89,
      98
    ]
  },
  "entite_4": {
    "label": "LOC",
    "text": "Couché",
    "jalons": [
      122,
      129
    ]
  },
  "entite_5": {
    "label": "LOC",
    "text": "Registre de la Compagnie de Coulons",
    "jalons": [
      137,
      172
    ]
  },
  "entite_6": {
    "label": "LOC",
    "text": "Connoissance",
    "jalons": [
      179,
      191
    ]
  },
  "entite_7": {
    "label": "PER",
    "text": "Jean françois Monpas",
    "jalons": [
      202,
      223
    ]
  },
  "entite_8": {
    "label": "PER",
    "text": "Dumas",
    "jalons": [
      228,
      233
    ]
  },
  "entite_9": {
    "label": "PER",
    "text": "Est fils",
    "jalons": [
      235,
      243
    ]
  },
  "entite_10": {
    "label": "PER",
    "text": "Martin Monpas",
    "jalons": [
      247,
      260
    ]
  },
  "entite_11": {
    "label": "PER",
    "text": "Margueritte Bertenieur",
    "jalons": [
      267,
      289
    ]
  },
  "entite_12": {
    "label": "MISC",
    "text": "S^t",
    "jalons": [
      299,
      302
    ]
  },
  "entite_13": {
    "label": "PER",
    "text": "Martin",
    "jalons": [
      303,
      309
    ]
  },
  "entite_14": {
    "label": "PER",
    "text": "Darras",
    "jalons": [
      338,
      344
    ]
  },
  "entite_15": {
    "label": "PER",
    "text": "Taille Cinqper",
    "jalons": [
      369,
      383
    ]
  },
  "entite_16": {
    "label": "ORG",
    "text": "Jardinier Interrogé",
    "jalons": [
      471,
      491
    ]
  },
  "entite_17": {
    "label": "PER",
    "text": "Repondu",
    "jalons": [
      621,
      628
    ]
  },
  "entite_18": {
    "label": "LOC",
    "text": "Connoissance",
    "jalons": [
      647,
      659
    ]
  },
  "entite_19": {
    "label": "MISC",
    "text": "accusé",
    "jalons": [
      686,
      693
    ]
  },
  "entite_20": {
    "label": "ORG",
    "text": "Interrogé",
    "jalons": [
      769,
      779
    ]
  },
  "entite_21": {
    "label": "LOC",
    "text": "Connoissance",
    "jalons": [
      803,
      815
    ]
  },
  "entite_22": {
    "label": "PER",
    "text": "Repondu",
    "jalons": [
      937,
      944
    ]
  },
  "entite_23": {
    "label": "PER",
    "text": "Connoissance de Cela",
    "jalons": [
      963,
      983
    ]
  },
  "entite_24": {
    "label": "PER",
    "text": "Deposer",
    "jalons": [
      1011,
      1018
    ]
  },
  "entite_25": {
    "label": "MISC",
    "text": "Contre l&#39;accusé",
    "jalons": [
      1027,
      1047
    ]
  },
  "entite_26": {
    "label": "MISC",
    "text": "obligé",
    "jalons": [
      1055,
      1062
    ]
  },
  "entite_27": {
    "label": "PER",
    "text": "Repondu",
    "jalons": [
      1176,
      1183
    ]
  },
  "entite_28": {
    "label": "PER",
    "text": "Deposer",
    "jalons": [
      1208,
      1215
    ]
  },
  "entite_29": {
    "label": "MISC",
    "text": "Contre le dit accusé",
    "jalons": [
      1227,
      1248
    ]
  },
  "entite_30": {
    "label": "ORG",
    "text": "Deposition",
    "jalons": [
      1275,
      1285
    ]
  },
  "entite_31": {
    "label": "ORG",
    "text": "Icelle Cinq",
    "jalons": [
      1292,
      1303
    ]
  },
  "entite_32": {
    "label": "MISC",
    "text": "Se Al pes",
    "jalons": [
      1321,
      1330
    ]
  },
  "entite_33": {
    "label": "ORG",
    "text": "Catt Lu",
    "jalons": [
      1348,
      1355
    ]
  }
}