{
  "entite_0": {
    "label": "LOC",
    "text": "Bordeaux",
    "jalons": [
      0,
      8
    ]
  },
  "entite_1": {
    "label": "PER",
    "text": "Monsieur e M^re Lheureus",
    "jalons": [
      24,
      48
    ]
  },
  "entite_2": {
    "label": "LOC",
    "text": "lay Laulnay",
    "jalons": [
      66,
      77
    ]
  },
  "entite_3": {
    "label": "PER",
    "text": "Riviere",
    "jalons": [
      114,
      121
    ]
  },
  "entite_4": {
    "label": "LOC",
    "text": "Nre",
    "jalons": [
      145,
      148
    ]
  },
  "entite_5": {
    "label": "MISC",
    "text": "Compte &amp",
    "jalons": [
      160,
      171
    ]
  },
  "entite_6": {
    "label": "PER",
    "text": "M Lemaal",
    "jalons": [
      183,
      191
    ]
  },
  "entite_7": {
    "label": "MISC",
    "text": "Commus &amp",
    "jalons": [
      253,
      264
    ]
  },
  "entite_8": {
    "label": "LOC",
    "text": "Bques",
    "jalons": [
      269,
      274
    ]
  },
  "entite_9": {
    "label": "PER",
    "text": "Enmagasin",
    "jalons": [
      308,
      317
    ]
  },
  "entite_10": {
    "label": "MISC",
    "text": "Bonté &amp",
    "jalons": [
      429,
      440
    ]
  },
  "entite_11": {
    "label": "MISC",
    "text": "Confiance",
    "jalons": [
      445,
      454
    ]
  },
  "entite_12": {
    "label": "LOC",
    "text": "m&#39;honnorez aussy",
    "jalons": [
      465,
      485
    ]
  },
  "entite_13": {
    "label": "PER",
    "text": "M Denolivas",
    "jalons": [
      532,
      543
    ]
  },
  "entite_14": {
    "label": "MISC",
    "text": "En mee le p^er de Ce mois du depuis les vents luy",
    "jalons": [
      549,
      598
    ]
  },
  "entite_15": {
    "label": "LOC",
    "text": "Liberté",
    "jalons": [
      655,
      663
    ]
  },
  "entite_16": {
    "label": "MISC",
    "text": "Colans",
    "jalons": [
      675,
      681
    ]
  },
  "entite_17": {
    "label": "PER",
    "text": "Eté Envoyez",
    "jalons": [
      692,
      704
    ]
  },
  "entite_18": {
    "label": "PER",
    "text": "M^r Provenchere",
    "jalons": [
      757,
      772
    ]
  },
  "entite_19": {
    "label": "ORG",
    "text": "Interets",
    "jalons": [
      829,
      837
    ]
  },
  "entite_20": {
    "label": "ORG",
    "text": "Conseil du port",
    "jalons": [
      875,
      890
    ]
  },
  "entite_21": {
    "label": "MISC",
    "text": "Etre renvoyés au Cap",
    "jalons": [
      906,
      927
    ]
  },
  "entite_22": {
    "label": "PER",
    "text": "Etre Juges",
    "jalons": [
      933,
      943
    ]
  },
  "entite_23": {
    "label": "ORG",
    "text": "Conseil dudit rieu",
    "jalons": [
      951,
      969
    ]
  },
  "entite_24": {
    "label": "MISC",
    "text": "Nous avons un nouvel archéveque",
    "jalons": [
      970,
      1002
    ]
  },
  "entite_25": {
    "label": "MISC",
    "text": "Eté accomptis",
    "jalons": [
      1036,
      1050
    ]
  },
  "entite_26": {
    "label": "MISC",
    "text": "Eté quelqu&#39;un",
    "jalons": [
      1064,
      1082
    ]
  },
  "entite_27": {
    "label": "LOC",
    "text": "Respectable",
    "jalons": [
      1092,
      1103
    ]
  },
  "entite_28": {
    "label": "MISC",
    "text": "En général",
    "jalons": [
      1117,
      1129
    ]
  },
  "entite_29": {
    "label": "MISC",
    "text": "Bien &amp",
    "jalons": [
      1143,
      1152
    ]
  },
  "entite_30": {
    "label": "PER",
    "text": "Madame la Marquise",
    "jalons": [
      1178,
      1196
    ]
  },
  "entite_31": {
    "label": "MISC",
    "text": "Rochefoucault Bayers",
    "jalons": [
      1225,
      1245
    ]
  }
}