{
  "voc_eval_res": {
    "precision": 44.0,
    "recall": 55.0,
    "f-score": 48.8889
  },
  "KL_res": {
    "KL divergence": 2.568824621258396,
    "Euclidean Dist.": 0.2867190103357878,
    "WER": 1.0,
    "CER": 0.6838709677419355,
    "Cosine Dist.": 0.33817747864419456
  },
  "occ_eval_res": {
    "precision": 41.0256,
    "recall": 55.1724,
    "f-score": 47.0588
  },
  "clean_eval": {
    "f-score": 12.589928057553958,
    "precision": 15.217391304347828,
    "recall": 10.736196319018406,
    "tp": 35,
    "fp": 195,
    "fn": 291
  },
  "jaccard": [
    0.5150501672240803
  ],
  "braycurtis": [
    0.44285714285714284
  ],
  "dice": [
    0.34684684684684686
  ],
  "cosinus": [
    0.3357895749856641
  ]
}