{
  "entite_0": {
    "label": "PER",
    "text": "Monieeur le Poieur",
    "jalons": [
      0,
      18
    ]
  },
  "entite_1": {
    "label": "LOC",
    "text": "Colonies",
    "jalons": [
      172,
      180
    ]
  },
  "entite_2": {
    "label": "MISC",
    "text": "Depositaire–",
    "jalons": [
      478,
      490
    ]
  },
  "entite_3": {
    "label": "ORG",
    "text": "d^e",
    "jalons": [
      498,
      501
    ]
  },
  "entite_4": {
    "label": "LOC",
    "text": "Notarce",
    "jalons": [
      664,
      671
    ]
  }
}