{
  "voc_eval_res": {
    "precision": 100.0,
    "recall": 75.0,
    "f-score": 85.7143
  },
  "KL_res": {
    "KL divergence": 1.3336133453462589,
    "Euclidean Dist.": 0.32274861218395146,
    "WER": 0.25,
    "CER": 0.26666666666666666,
    "Cosine Dist.": 0.07417990022744869
  },
  "occ_eval_res": {
    "precision": 100.0,
    "recall": 75.0,
    "f-score": 85.7143
  },
  "clean_eval": {
    "f-score": 51.94805194805194,
    "precision": 40.0,
    "recall": 74.07407407407408,
    "tp": 20,
    "fp": 30,
    "fn": 7
  },
  "jaccard": [
    0.2807017543859649
  ],
  "braycurtis": [
    0.16326530612244897
  ],
  "dice": [
    0.16326530612244897
  ],
  "cosinus": [
    0.15188547612127623
  ]
}