{
  "entite_0": {
    "label": "MISC",
    "text": "Colonies Dupare",
    "jalons": [
      0,
      15
    ]
  },
  "entite_1": {
    "label": "LOC",
    "text": "Amman",
    "jalons": [
      99,
      104
    ]
  },
  "entite_2": {
    "label": "LOC",
    "text": "Rappellé",
    "jalons": [
      210,
      219
    ]
  },
  "entite_3": {
    "label": "PER",
    "text": "aupoint",
    "jalons": [
      465,
      472
    ]
  },
  "entite_4": {
    "label": "PER",
    "text": "Monseigneur",
    "jalons": [
      534,
      545
    ]
  },
  "entite_5": {
    "label": "ORG",
    "text": "Copie",
    "jalons": [
      554,
      559
    ]
  }
}