{
  "entite_0": {
    "label": "MISC",
    "text": "l&#x27;an",
    "jalons": [
      117,
      126
    ]
  },
  "entite_1": {
    "label": "ORG",
    "text": "Bureau",
    "jalons": [
      223,
      229
    ]
  },
  "entite_2": {
    "label": "LOC",
    "text": "Invalides",
    "jalons": [
      264,
      273
    ]
  },
  "entite_3": {
    "label": "LOC",
    "text": "⟦",
    "jalons": [
      321,
      322
    ]
  },
  "entite_4": {
    "label": "ORG",
    "text": "C^n",
    "jalons": [
      360,
      363
    ]
  }
}