{
  "entite_0": {
    "label": "MISC",
    "text": "Domingue Proces",
    "jalons": [
      0,
      15
    ]
  },
  "entite_1": {
    "label": "LOC",
    "text": "Contumace",
    "jalons": [
      29,
      38
    ]
  },
  "entite_2": {
    "label": "PER",
    "text": "l&#39;année",
    "jalons": [
      91,
      103
    ]
  },
  "entite_3": {
    "label": "PER",
    "text": "Louis",
    "jalons": [
      148,
      153
    ]
  },
  "entite_4": {
    "label": "PER",
    "text": "henry",
    "jalons": [
      164,
      169
    ]
  },
  "entite_5": {
    "label": "PER",
    "text": "Roy",
    "jalons": [
      194,
      197
    ]
  },
  "entite_6": {
    "label": "PER",
    "text": "Louis",
    "jalons": [
      225,
      230
    ]
  },
  "entite_7": {
    "label": "MISC",
    "text": "afsisté",
    "jalons": [
      232,
      240
    ]
  },
  "entite_8": {
    "label": "MISC",
    "text": "Jean",
    "jalons": [
      252,
      256
    ]
  },
  "entite_9": {
    "label": "MISC",
    "text": "Requeste",
    "jalons": [
      305,
      313
    ]
  },
  "entite_10": {
    "label": "PER",
    "text": "Brach",
    "jalons": [
      360,
      365
    ]
  },
  "entite_11": {
    "label": "LOC",
    "text": "S^t",
    "jalons": [
      400,
      403
    ]
  },
  "entite_12": {
    "label": "PER",
    "text": "Loüis",
    "jalons": [
      404,
      410
    ]
  },
  "entite_13": {
    "label": "PER",
    "text": "Gouverneur",
    "jalons": [
      414,
      424
    ]
  },
  "entite_14": {
    "label": "LOC",
    "text": "Domingue",
    "jalons": [
      452,
      460
    ]
  },
  "entite_15": {
    "label": "LOC",
    "text": "Loüis",
    "jalons": [
      473,
      479
    ]
  },
  "entite_16": {
    "label": "MISC",
    "text": "Ch^er",
    "jalons": [
      491,
      496
    ]
  },
  "entite_17": {
    "label": "ORG",
    "text": "Coulons",
    "jalons": [
      500,
      507
    ]
  },
  "entite_18": {
    "label": "MISC",
    "text": "Jean",
    "jalons": [
      570,
      574
    ]
  },
  "entite_19": {
    "label": "PER",
    "text": "Dumas",
    "jalons": [
      597,
      602
    ]
  },
  "entite_20": {
    "label": "ORG",
    "text": "Depart",
    "jalons": [
      681,
      687
    ]
  },
  "entite_21": {
    "label": "PER",
    "text": "S^s",
    "jalons": [
      817,
      820
    ]
  },
  "entite_22": {
    "label": "PER",
    "text": "Brach",
    "jalons": [
      824,
      829
    ]
  },
  "entite_23": {
    "label": "MISC",
    "text": "Comparu",
    "jalons": [
      888,
      895
    ]
  },
  "entite_24": {
    "label": "LOC",
    "text": "jouy",
    "jalons": [
      921,
      925
    ]
  },
  "entite_25": {
    "label": "PER",
    "text": "Temoin",
    "jalons": [
      968,
      974
    ]
  },
  "entite_26": {
    "label": "LOC",
    "text": "Chatains",
    "jalons": [
      1039,
      1047
    ]
  },
  "entite_27": {
    "label": "LOC",
    "text": "Bouché",
    "jalons": [
      1086,
      1093
    ]
  },
  "entite_28": {
    "label": "ORG",
    "text": "soucils–",
    "jalons": [
      1136,
      1144
    ]
  },
  "entite_29": {
    "label": "PER",
    "text": "Barbe",
    "jalons": [
      1148,
      1153
    ]
  },
  "entite_30": {
    "label": "LOC",
    "text": "Chatains",
    "jalons": [
      1154,
      1162
    ]
  },
  "entite_31": {
    "label": "MISC",
    "text": "luypreté",
    "jalons": [
      1191,
      1200
    ]
  },
  "entite_32": {
    "label": "MISC",
    "text": "Celluy",
    "jalons": [
      1262,
      1268
    ]
  }
}