{
  "entite_0": {
    "label": "LOC",
    "text": "Tache",
    "jalons": [
      46,
      51
    ]
  },
  "entite_1": {
    "label": "LOC",
    "text": "Espagnolle",
    "jalons": [
      71,
      81
    ]
  },
  "entite_2": {
    "label": "PER",
    "text": "netre",
    "jalons": [
      153,
      158
    ]
  },
  "entite_3": {
    "label": "PER",
    "text": "Tache",
    "jalons": [
      211,
      216
    ]
  },
  "entite_4": {
    "label": "PER",
    "text": "S^t",
    "jalons": [
      351,
      354
    ]
  },
  "entite_5": {
    "label": "PER",
    "text": "Monsieur",
    "jalons": [
      599,
      607
    ]
  },
  "entite_6": {
    "label": "MISC",
    "text": "Etably",
    "jalons": [
      691,
      697
    ]
  },
  "entite_7": {
    "label": "PER",
    "text": "luy",
    "jalons": [
      701,
      704
    ]
  },
  "entite_8": {
    "label": "PER",
    "text": "sil",
    "jalons": [
      713,
      716
    ]
  },
  "entite_9": {
    "label": "PER",
    "text": "deposant",
    "jalons": [
      796,
      804
    ]
  },
  "entite_10": {
    "label": "PER",
    "text": "Monsieur",
    "jalons": [
      837,
      845
    ]
  },
  "entite_11": {
    "label": "MISC",
    "text": "Etably",
    "jalons": [
      912,
      918
    ]
  },
  "entite_12": {
    "label": "MISC",
    "text": "jl",
    "jalons": [
      994,
      996
    ]
  },
  "entite_13": {
    "label": "PER",
    "text": "Tache",
    "jalons": [
      1023,
      1028
    ]
  },
  "entite_14": {
    "label": "PER",
    "text": "Tache",
    "jalons": [
      1125,
      1130
    ]
  },
  "entite_15": {
    "label": "PER",
    "text": "Tache",
    "jalons": [
      1230,
      1235
    ]
  },
  "entite_16": {
    "label": "LOC",
    "text": "Tache",
    "jalons": [
      1319,
      1324
    ]
  },
  "entite_17": {
    "label": "LOC",
    "text": "Luy",
    "jalons": [
      1328,
      1331
    ]
  }
}