{
  "entite_0": {
    "label": "LOC",
    "text": "Damas Gouvieneur",
    "jalons": [
      114,
      130
    ]
  },
  "entite_1": {
    "label": "MISC",
    "text": "La Martinique Jai L&#39;honneur",
    "jalons": [
      133,
      164
    ]
  },
  "entite_2": {
    "label": "MISC",
    "text": "M",
    "jalons": [
      184,
      185
    ]
  },
  "entite_3": {
    "label": "PER",
    "text": "Roy",
    "jalons": [
      194,
      197
    ]
  },
  "entite_4": {
    "label": "MISC",
    "text": "S^r Joly Garde D&#39;artillene",
    "jalons": [
      222,
      252
    ]
  },
  "entite_5": {
    "label": "MISC",
    "text": "S^t Pierre",
    "jalons": [
      256,
      266
    ]
  },
  "entite_6": {
    "label": "MISC",
    "text": "La médaille d&#39;ou",
    "jalons": [
      268,
      289
    ]
  },
  "entite_7": {
    "label": "PER",
    "text": "M. de Senneville",
    "jalons": [
      405,
      421
    ]
  }
}